Workbook

Sheet Resumen
A1: Propuesta inicial de asignación de actividades — PAC Medellín
A2: Base editable para validación con líderes. Cada entregable: 85% elaboración + 10% revisión María José/Guillermo + 5% revisión final Juana–SMA.
A4: Componente | B4: ID | C4: Entregable | D4: N.º actividades | E4: Elaboración | F4: Revisión y aval | G4: Revisión SMA | H4: Total
A5: C1 | B5: P1 | C5: Documento de caracterización socioeconómica, vulnerabilidad y brechas de equidad para la acción climática | D5: =COUNTIF('Asignación detallada'!$C$5:$C$200,B5) -> 8 | E5: =SUMIFS('Asignación detallada'!$J$5:$J$200,'Asignación detallada'!$C$5:$C$200,B5,'Asignación detallada'!$F$5:$F$200,"Elaboración") -> 0.85 | F5: =SUMIFS('Asignación detallada'!$J$5:$J$200,'Asignación detallada'!$C$5:$C$200,B5,'Asignación detallada'!$F$5:$F$200,"Revisión y aval") -> 0.1 | G5: =SUMIFS('Asignación detallada'!$J$5:$J$200,'Asignación detallada'!$C$5:$C$200,B5,'Asignación detallada'!$F$5:$F$200,"Revisión final Secretaría") -> 0.05 | H5: =ROUND(SUM(E5:G5),2) -> 1
A6: C1 | B6: P2 | C6: Capítulo de diagnóstico y prospectiva climática consolidado | D6: =COUNTIF('Asignación detallada'!$C$5:$C$200,B6) -> 7 | E6: =SUMIFS('Asignación detallada'!$J$5:$J$200,'Asignación detallada'!$C$5:$C$200,B6,'Asignación detallada'!$F$5:$F$200,"Elaboración") -> 0.85 | F6: =SUMIFS('Asignación detallada'!$J$5:$J$200,'Asignación detallada'!$C$5:$C$200,B6,'Asignación detallada'!$F$5:$F$200,"Revisión y aval") -> 0.1 | G6: =SUMIFS('Asignación detallada'!$J$5:$J$200,'Asignación detallada'!$C$5:$C$200,B6,'Asignación detallada'!$F$5:$F$200,"Revisión final Secretaría") -> 0.05 | H6: =ROUND(SUM(E6:G6),2) -> 1
A7: C2 | B7: P3 | C7: Capítulo de direccionamiento estratégico del PAC ajustado | D7: =COUNTIF('Asignación detallada'!$C$5:$C$200,B7) -> 8 | E7: =SUMIFS('Asignación detallada'!$J$5:$J$200,'Asignación detallada'!$C$5:$C$200,B7,'Asignación detallada'!$F$5:$F$200,"Elaboración") -> 0.85 | F7: =SUMIFS('Asignación detallada'!$J$5:$J$200,'Asignación detallada'!$C$5:$C$200,B7,'Asignación detallada'!$F$5:$F$200,"Revisión y aval") -> 0.1 | G7: =SUMIFS('Asignación detallada'!$J$5:$J$200,'Asignación detallada'!$C$5:$C$200,B7,'Asignación detallada'!$F$5:$F$200,"Revisión final Secretaría") -> 0.05 | H7: =ROUND(SUM(E7:G7),2) -> 1
A8: C2 | B8: P4 | C8: Matriz de coherencia estratégica del Plan | D8: =COUNTIF('Asignación detallada'!$C$5:$C$200,B8) -> 7 | E8: =SUMIFS('Asignación detallada'!$J$5:$J$200,'Asignación detallada'!$C$5:$C$200,B8,'Asignación detallada'!$F$5:$F$200,"Elaboración") -> 0.85 | F8: =SUMIFS('Asignación detallada'!$J$5:$J$200,'Asignación detallada'!$C$5:$C$200,B8,'Asignación detallada'!$F$5:$F$200,"Revisión y aval") -> 0.1 | G8: =SUMIFS('Asignación detallada'!$J$5:$J$200,'Asignación detallada'!$C$5:$C$200,B8,'Asignación detallada'!$F$5:$F$200,"Revisión final Secretaría") -> 0.05 | H8: =ROUND(SUM(E8:G8),2) -> 1
A9: C3 | B9: P5 | C9: Catálogo caracterizado de medidas de mitigación y adaptación | D9: =COUNTIF('Asignación detallada'!$C$5:$C$200,B9) -> 9 | E9: =SUMIFS('Asignación detallada'!$J$5:$J$200,'Asignación detallada'!$C$5:$C$200,B9,'Asignación detallada'!$F$5:$F$200,"Elaboración") -> 0.85 | F9: =SUMIFS('Asignación detallada'!$J$5:$J$200,'Asignación detallada'!$C$5:$C$200,B9,'Asignación detallada'!$F$5:$F$200,"Revisión y aval") -> 0.1 | G9: =SUMIFS('Asignación detallada'!$J$5:$J$200,'Asignación detallada'!$C$5:$C$200,B9,'Asignación detallada'!$F$5:$F$200,"Revisión final Secretaría") -> 0.05 | H9: =ROUND(SUM(E9:G9),2) -> 1
A10: C3 | B10: P6 | C10: Documento técnico de priorización de medidas mediante AHP/ANP | D10: =COUNTIF('Asignación detallada'!$C$5:$C$200,B10) -> 8 | E10: =SUMIFS('Asignación detallada'!$J$5:$J$200,'Asignación detallada'!$C$5:$C$200,B10,'Asignación detallada'!$F$5:$F$200,"Elaboración") -> 0.85 | F10: =SUMIFS('Asignación detallada'!$J$5:$J$200,'Asignación detallada'!$C$5:$C$200,B10,'Asignación detallada'!$F$5:$F$200,"Revisión y aval") -> 0.1 | G10: =SUMIFS('Asignación detallada'!$J$5:$J$200,'Asignación detallada'!$C$5:$C$200,B10,'Asignación detallada'!$F$5:$F$200,"Revisión final Secretaría") -> 0.05 | H10: =ROUND(SUM(E10:G10),2) -> 1
A11: C3 | B11: P7 | C11: Hoja de ruta de descarbonización y resiliencia climática al 2050 | D11: =COUNTIF('Asignación detallada'!$C$5:$C$200,B11) -> 8 | E11: =SUMIFS('Asignación detallada'!$J$5:$J$200,'Asignación detallada'!$C$5:$C$200,B11,'Asignación detallada'!$F$5:$F$200,"Elaboración") -> 0.85 | F11: =SUMIFS('Asignación detallada'!$J$5:$J$200,'Asignación detallada'!$C$5:$C$200,B11,'Asignación detallada'!$F$5:$F$200,"Revisión y aval") -> 0.1 | G11: =SUMIFS('Asignación detallada'!$J$5:$J$200,'Asignación detallada'!$C$5:$C$200,B11,'Asignación detallada'!$F$5:$F$200,"Revisión final Secretaría") -> 0.05 | H11: =ROUND(SUM(E11:G11),2) -> 1
A12: C4 | B12: P8 | C12: Hoja de articulación con el sistema de CTeI y agenda de innovación | D12: =COUNTIF('Asignación detallada'!$C$5:$C$200,B12) -> 8 | E12: =SUMIFS('Asignación detallada'!$J$5:$J$200,'Asignación detallada'!$C$5:$C$200,B12,'Asignación detallada'!$F$5:$F$200,"Elaboración") -> 0.85 | F12: =SUMIFS('Asignación detallada'!$J$5:$J$200,'Asignación detallada'!$C$5:$C$200,B12,'Asignación detallada'!$F$5:$F$200,"Revisión y aval") -> 0.1 | G12: =SUMIFS('Asignación detallada'!$J$5:$J$200,'Asignación detallada'!$C$5:$C$200,B12,'Asignación detallada'!$F$5:$F$200,"Revisión final Secretaría") -> 0.05 | H12: =ROUND(SUM(E12:G12),2) -> 1
A13: C4 | B13: P9 | C13: Sistema de Gobierno de Datos Climáticos, indicadores y dashboard MERL | D13: =COUNTIF('Asignación detallada'!$C$5:$C$200,B13) -> 8 | E13: =SUMIFS('Asignación detallada'!$J$5:$J$200,'Asignación detallada'!$C$5:$C$200,B13,'Asignación detallada'!$F$5:$F$200,"Elaboración") -> 0.85 | F13: =SUMIFS('Asignación detallada'!$J$5:$J$200,'Asignación detallada'!$C$5:$C$200,B13,'Asignación detallada'!$F$5:$F$200,"Revisión y aval") -> 0.1 | G13: =SUMIFS('Asignación detallada'!$J$5:$J$200,'Asignación detallada'!$C$5:$C$200,B13,'Asignación detallada'!$F$5:$F$200,"Revisión final Secretaría") -> 0.05 | H13: =ROUND(SUM(E13:G13),2) -> 1
A14: C4 | B14: P10 | C14: Asistente inteligente para consulta y trazabilidad de información climática | D14: =COUNTIF('Asignación detallada'!$C$5:$C$200,B14) -> 8 | E14: =SUMIFS('Asignación detallada'!$J$5:$J$200,'Asignación detallada'!$C$5:$C$200,B14,'Asignación detallada'!$F$5:$F$200,"Elaboración") -> 0.85 | F14: =SUMIFS('Asignación detallada'!$J$5:$J$200,'Asignación detallada'!$C$5:$C$200,B14,'Asignación detallada'!$F$5:$F$200,"Revisión y aval") -> 0.1 | G14: =SUMIFS('Asignación detallada'!$J$5:$J$200,'Asignación detallada'!$C$5:$C$200,B14,'Asignación detallada'!$F$5:$F$200,"Revisión final Secretaría") -> 0.05 | H14: =ROUND(SUM(E14:G14),2) -> 1
A15: C5 | B15: P11 | C15: Matriz de gestión de riesgos y barreras para la implementación | D15: =COUNTIF('Asignación detallada'!$C$5:$C$200,B15) -> 8 | E15: =SUMIFS('Asignación detallada'!$J$5:$J$200,'Asignación detallada'!$C$5:$C$200,B15,'Asignación detallada'!$F$5:$F$200,"Elaboración") -> 0.85 | F15: =SUMIFS('Asignación detallada'!$J$5:$J$200,'Asignación detallada'!$C$5:$C$200,B15,'Asignación detallada'!$F$5:$F$200,"Revisión y aval") -> 0.1 | G15: =SUMIFS('Asignación detallada'!$J$5:$J$200,'Asignación detallada'!$C$5:$C$200,B15,'Asignación detallada'!$F$5:$F$200,"Revisión final Secretaría") -> 0.05 | H15: =ROUND(SUM(E15:G15),2) -> 1
A16: C5 | B16: P12 | C16: Cartera priorizada de proyectos climáticos bancables | D16: =COUNTIF('Asignación detallada'!$C$5:$C$200,B16) -> 8 | E16: =SUMIFS('Asignación detallada'!$J$5:$J$200,'Asignación detallada'!$C$5:$C$200,B16,'Asignación detallada'!$F$5:$F$200,"Elaboración") -> 0.85 | F16: =SUMIFS('Asignación detallada'!$J$5:$J$200,'Asignación detallada'!$C$5:$C$200,B16,'Asignación detallada'!$F$5:$F$200,"Revisión y aval") -> 0.1 | G16: =SUMIFS('Asignación detallada'!$J$5:$J$200,'Asignación detallada'!$C$5:$C$200,B16,'Asignación detallada'!$F$5:$F$200,"Revisión final Secretaría") -> 0.05 | H16: =ROUND(SUM(E16:G16),2) -> 1
... A22: C6 | B22: P18 | C22: Documento divulgativo de la Evaluación de Riesgos Climáticos | D22: =COUNTIF('Asignación detallada'!$C$5:$C$200,B22) -> 8 | E22: =SUMIFS('Asignación detallada'!$J$5:$J$200,'Asignación detallada'!$C$5:$C$200,B22,'Asignación detallada'!$F$5:$F$200,"Elaboración") -> 0.85 | F22: =SUMIFS('Asignación detallada'!$J$5:$J$200,'Asignación detallada'!$C$5:$C$200,B22,'Asignación detallada'!$F$5:$F$200,"Revisión y aval") -> 0.1 | G22: =SUMIFS('Asignación detallada'!$J$5:$J$200,'Asignación detallada'!$C$5:$C$200,B22,'Asignación detallada'!$F$5:$F$200,"Revisión final Secretaría") -> 0.05 | H22: =ROUND(SUM(E22:G22),2) -> 1

Sheet Asignación detallada
A1: Matriz detallada de actividades, responsables, pesos, fechas y evidencias
A2: Fechas propuestas a partir de la línea base de la plataforma PAC; deben validarse con los responsables. Los pesos corresponden a actividades del entregable, no a honorarios.
A4: Comp. | B4: Componente | C4: ID entregable | D4: Entregable | E4: ID actividad | F4: Etapa | G4: Actividad específica | H4: Responsable(s) principal(es) | I4: Apoyos | J4: Peso | K4: Fecha inicio | L4: Fecha fin | M4: Evidencia / criterio de terminado | N4: Actividad contractual de origen | O4: Observación
A5: C1 | B5: Evidencia, Diagnóstico y Prospectiva Climática | C5: P1 | D5: Documento de caracterización socioeconómica, vulnerabilidad y brechas de equidad para la acción climática | E5: P1-A01 | F5: Elaboración | G5: Revisar y organizar los insumos documentales, bases y antecedentes requeridos para la caracterización | H5: Sebastián Cartagena y Marcos Arango Tamayo | I5: Paola Andrea Ruiz Franco | J5: 0.15 | K5: 46251.708 | L5: 46258.708 | M5: Matriz de fuentes e insumos con vacíos identificados | N5: Evidencia climática, trayectorias de emisiones, riesgos climáticos, caracterización socioeconómica y vulnerabilidad territorial. | O5: Propuesta inicial
A6: C1 | B6: Evidencia, Diagnóstico y Prospectiva Climática | C6: P1 | D6: Documento de caracterización socioeconómica, vulnerabilidad y brechas de equidad para la acción climática | E6: P1-A02 | F6: Elaboración | G6: Consolidar inventarios de GEI y analizar trayectorias de emisiones 2030, 2040 y 2050 | H6: Juliana Valencia | I6: Marcos Arango Tamayo | J6: 0.2 | K6: 46252.708 | L6: 46262.708 | M6: Memoria técnica, tablas y gráficos de emisiones | N6: Evidencia climática, trayectorias de emisiones, riesgos climáticos, caracterización socioeconómica y vulnerabilidad territorial. | O6: Propuesta inicial
A7: C1 | B7: Evidencia, Diagnóstico y Prospectiva Climática | C7: P1 | D7: Documento de caracterización socioeconómica, vulnerabilidad y brechas de equidad para la acción climática | E7: P1-A03 | F7: Elaboración | G7: Integrar riesgos climáticos, adaptación, recurso hídrico, biodiversidad y soluciones basadas en la naturaleza | H7: Vanessa García Leoz y Jeiner de Jesús Castellanos Barliza | I7: Harlem Acevedo Agudelo | J7: 0.15 | K7: 46254.708 | L7: 46265.708 | M7: Sección técnica integrada y matriz de hallazgos | N7: Evidencia climática, trayectorias de emisiones, riesgos climáticos, caracterización socioeconómica y vulnerabilidad territorial. | O7: Propuesta inicial
A8: C1 | B8: Evidencia, Diagnóstico y Prospectiva Climática | C8: P1 | D8: Documento de caracterización socioeconómica, vulnerabilidad y brechas de equidad para la acción climática | E8: P1-A04 | F8: Elaboración | G8: Desarrollar la caracterización socioeconómica con enfoque diferencial, equidad y justicia climática | H8: Sebastián Cartagena | I8: Paola Andrea Ruiz Franco | J8: 0.15 | K8: 46256.708 | L8: 46268.708 | M8: Sección socioeconómica y matriz de población vulnerable | N8: Evidencia climática, trayectorias de emisiones, riesgos climáticos, caracterización socioeconómica y vulnerabilidad territorial. | O8: Propuesta inicial
A9: C1 | B9: Evidencia, Diagnóstico y Prospectiva Climática | C9: P1 | D9: Documento de caracterización socioeconómica, vulnerabilidad y brechas de equidad para la acción climática | E9: P1-A05 | F9: Elaboración | G9: Realizar el análisis territorial y geoespacial de vulnerabilidad y capacidad adaptativa | H9: Marcos Arango Tamayo | I9: Jeiner de Jesús Castellanos Barliza | J9: 0.1 | K9: 46260.708 | L9: 46272.708 | M9: Mapas, capas y síntesis territorial | N9: Evidencia climática, trayectorias de emisiones, riesgos climáticos, caracterización socioeconómica y vulnerabilidad territorial. | O9: Propuesta inicial
A10: C1 | B10: Evidencia, Diagnóstico y Prospectiva Climática | C10: P1 | D10: Documento de caracterización socioeconómica, vulnerabilidad y brechas de equidad para la acción climática | E10: P1-A06 | F10: Elaboración | G10: Integrar y redactar el documento de caracterización | H10: Paola Andrea Ruiz Franco | I10: Juliana Valencia y Sebastián Cartagena | J10: 0.1 | K10: 46265.708 | L10: 46275.708 | M10: Borrador técnico completo de P1 | N10: Evidencia climática, trayectorias de emisiones, riesgos climáticos, caracterización socioeconómica y vulnerabilidad territorial. | O10: Propuesta inicial
A11: C1 | B11: Evidencia, Diagnóstico y Prospectiva Climática | C11: P1 | D11: Documento de caracterización socioeconómica, vulnerabilidad y brechas de equidad para la acción climática | E11: P1-R01 | F11: Revisión y aval | G11: Revisar integralmente la calidad técnica, coherencia, trazabilidad contractual y suficiencia del entregable | H11: María José Suárez y Guillermo Penagos | I11: Responsables técnicos del entregable | J11: 0.1 | K11: 46276.708 | L11: 46278.708 | M11: Concepto consolidado de revisión y aval | N11: Control de calidad previo al envío oficial | O11: Propuesta inicial
A12: C1 | B12: Evidencia, Diagnóstico y Prospectiva Climática | C12: P1 | D12: Documento de caracterización socioeconómica, vulnerabilidad y brechas de equidad para la acción climática | E12: P1-R02 | F12: Revisión final Secretaría | G12: Realizar la revisión final institucional y emitir observaciones o conformidad para el cierre del entregable | H12: Juana — Secretaría de Medio Ambiente | I12: María José Suárez y Paola Andrea Ruiz Franco | J12: 0.05 | K12: 46279.708 | L12: 46282.708 | M12: Concepto u observaciones finales de la Secretaría | N12: Revisión final antes del cierre oficial | O12: Nombre completo de Juana por confirmar
A13: C1 | B13: Evidencia, Diagnóstico y Prospectiva Climática | C13: P2 | D13: Capítulo de diagnóstico y prospectiva climática consolidado | E13: P2-A01 | F13: Elaboración | G13: Revisar la consistencia y suficiencia de los insumos que alimentan el diagnóstico consolidado | H13: Sebastián Cartagena y Marcos Arango Tamayo | I13: Paola Andrea Ruiz Franco | J13: 0.15 | K13: 46251.708 | L13: 46262.708 | M13: Lista de chequeo y matriz de vacíos | N13: Consolidación del diagnóstico y la prospectiva climática a partir de la evidencia generada para C1. | O13: Propuesta inicial
A14: C1 | B14: Evidencia, Diagnóstico y Prospectiva Climática | C14: P2 | D14: Capítulo de diagnóstico y prospectiva climática consolidado | E14: P2-A02 | F14: Elaboración | G14: Consolidar la evidencia climática, hidrológica y las trayectorias de emisiones | H14: Juliana Valencia | I14: Marcos Arango Tamayo | J14: 0.2 | K14: 46253.708 | L14: 46268.708 | M14: Síntesis de evidencia y escenarios | N14: Consolidación del diagnóstico y la prospectiva climática a partir de la evidencia generada para C1. | O14: Propuesta inicial
A15: C1 | B15: Evidencia, Diagnóstico y Prospectiva Climática | C15: P2 | D15: Capítulo de diagnóstico y prospectiva climática consolidado | E15: P2-A03 | F15: Elaboración | G15: Integrar los resultados de vulnerabilidad, adaptación, biodiversidad y recurso hídrico | H15: Vanessa García Leoz | I15: Jeiner de Jesús Castellanos Barliza y Harlem Acevedo Agudelo | J15: 0.15 | K15: 46257.708 | L15: 46273.708 | M15: Síntesis de vulnerabilidad y adaptación | N15: Consolidación del diagnóstico y la prospectiva climática a partir de la evidencia generada para C1. | O15: Propuesta inicial
A16: C1 | B16: Evidencia, Diagnóstico y Prospectiva Climática | C16: P2 | D16: Capítulo de diagnóstico y prospectiva climática consolidado | E16: P2-A04 | F16: Elaboración | G16: Construir la lectura prospectiva territorial y sectorial | H16: Marcos Arango Tamayo | I16: Juliana Valencia y Sebastián Cartagena | J16: 0.15 | K16: 46262.708 | L16: 46277.708 | M16: Escenarios y conclusiones prospectivas | N16: Consolidación del diagnóstico y la prospectiva climática a partir de la evidencia generada para C1. | O16: Propuesta inicial
... A147: C6 | B147: Participación, Gobernanza y Comunicación | C147: P18 | D147: Documento divulgativo de la Evaluación de Riesgos Climáticos | E147: P18-R02 | F147: Revisión final Secretaría | G147: Realizar la revisión final institucional y emitir observaciones o conformidad para el cierre del entregable | H147: Juana — Secretaría de Medio Ambiente | I147: María José Suárez y Paola Andrea Ruiz Franco | J147: 0.05 | K147: 46359.708 | L147: 46365.708 | M147: Concepto u observaciones finales de la Secretaría | N147: Revisión final antes del cierre oficial | O147: Nombre completo de Juana por confirmar

Sheet Perfiles
A1: Perfiles del equipo utilizados para la asignación
A3: Persona | B3: Perfil | C3: Fortalezas principales | D3: Uso propuesto en la matriz
A4: María José Suárez | B4: Director(a) del Proyecto | C4: Dirección técnica y administrativa; articulación institucional | D4: Revisión y aval transversal
A5: Paola Andrea Ruiz Franco | B5: Profesional de Coordinación Técnica | C5: Coordinación, seguimiento, sostenibilidad y proyectos CTeI | D5: Integración y coordinación técnica
A6: Juliana Valencia | B6: Consultora en Evidencia, Diagnóstico y Prospectiva Climática | C6: Modelación climática e hidrológica; escenarios | D6: Evidencia, emisiones y prospectiva
A7: Jeiner de Jesús Castellanos Barliza | B7: Consultor en SbN y Biodiversidad | C7: Ecología, restauración y soluciones basadas en la naturaleza | D7: Biodiversidad, SbN y adaptación
A8: Marcos Arango Tamayo | B8: Profesional de Apoyo Territorial y Geoespacial | C8: Hidrología, geoespacial y datos ambientales | D8: Territorialización, análisis y consolidación
A9: Diana Carolina Ríos Echeverri | B9: Consultora en Priorización Multicriterio | C9: Modelado cuantitativo y análisis de decisiones | D9: AHP/ANP, priorización y riesgos
A10: Harlem Acevedo Agudelo | B10: Consultor en Gestión de la Construcción | C10: Sostenibilidad, construcción, SbN y economía circular | D10: Medidas e implementación sostenible
A11: Vanessa García Leoz | B11: Consultora en Recurso Hídrico y Adaptación | C11: Ecohidrología, recurso hídrico y cambio climático | D11: Adaptación y resiliencia hídrica
A12: Alejandro Silva Cortés | B12: Consultor en Finanzas Climáticas | C12: Evaluación financiera y gestión del riesgo | D12: Costos, bancabilidad y financiación
A13: Guillermo Penagos | B13: Consultor en Planeación Climática, Política Pública y Equidad | C13: Planificación, equidad, gobernanza y participación | D13: Revisión técnica y de política pública
A14: Luis Eduardo Vahos Hernández | B14: Consultor en IA, Analítica y Transformación Digital | C14: IA, analítica de datos y transformación digital | D14: IA, dashboard y soluciones digitales
... A19: Juana — Secretaría de Medio Ambiente | B19: Revisora final institucional | C19: Revisión institucional del Distrito | D19: Revisión final del 5%
